JingtaiWangzhanGoujianShouceShiyongHugoGoujianGerenBoke/README.md
JingtaiWangzhanGoujianShouceShiyongHugoGoujianGerenBoke/__init__.py
JingtaiWangzhanGoujianShouceShiyongHugoGoujianGerenBoke/__main__.py
JingtaiWangzhanGoujianShouceShiyongHugoGoujianGerenBoke/file.epub
JingtaiWangzhanGoujianShouceShiyongHugoGoujianGerenBoke/index.html
JingtaiWangzhanGoujianShouceShiyongHugoGoujianGerenBoke/css/__init__.py
JingtaiWangzhanGoujianShouceShiyongHugoGoujianGerenBoke/css/annotations.css
JingtaiWangzhanGoujianShouceShiyongHugoGoujianGerenBoke/css/main.css
JingtaiWangzhanGoujianShouceShiyongHugoGoujianGerenBoke/css/normalize.css
JingtaiWangzhanGoujianShouceShiyongHugoGoujianGerenBoke/css/popup.css
JingtaiWangzhanGoujianShouceShiyongHugoGoujianGerenBoke/font/__init__.py
JingtaiWangzhanGoujianShouceShiyongHugoGoujianGerenBoke/font/fontello.eot
JingtaiWangzhanGoujianShouceShiyongHugoGoujianGerenBoke/font/fontello.svg
JingtaiWangzhanGoujianShouceShiyongHugoGoujianGerenBoke/font/fontello.ttf
JingtaiWangzhanGoujianShouceShiyongHugoGoujianGerenBoke/font/fontello.woff
JingtaiWangzhanGoujianShouceShiyongHugoGoujianGerenBoke/img/__init__.py
JingtaiWangzhanGoujianShouceShiyongHugoGoujianGerenBoke/img/annotator-glyph-sprite.png
JingtaiWangzhanGoujianShouceShiyongHugoGoujianGerenBoke/img/annotator-icon-sprite.png
JingtaiWangzhanGoujianShouceShiyongHugoGoujianGerenBoke/img/apple-touch-icon.png
JingtaiWangzhanGoujianShouceShiyongHugoGoujianGerenBoke/img/cancelfullscreen.png
JingtaiWangzhanGoujianShouceShiyongHugoGoujianGerenBoke/img/close.png
JingtaiWangzhanGoujianShouceShiyongHugoGoujianGerenBoke/img/fullscreen.png
JingtaiWangzhanGoujianShouceShiyongHugoGoujianGerenBoke/img/loader.gif
JingtaiWangzhanGoujianShouceShiyongHugoGoujianGerenBoke/img/menu-icon.png
JingtaiWangzhanGoujianShouceShiyongHugoGoujianGerenBoke/img/save.png
JingtaiWangzhanGoujianShouceShiyongHugoGoujianGerenBoke/img/saved.png
JingtaiWangzhanGoujianShouceShiyongHugoGoujianGerenBoke/img/settings-s.png
jingtai_wangzhan_goujian_shouce_shiyong_hugo_goujian_geren_boke-2024.3.3.0.dist-info/METADATA
jingtai_wangzhan_goujian_shouce_shiyong_hugo_goujian_geren_boke-2024.3.3.0.dist-info/WHEEL
jingtai_wangzhan_goujian_shouce_shiyong_hugo_goujian_geren_boke-2024.3.3.0.dist-info/entry_points.txt
jingtai_wangzhan_goujian_shouce_shiyong_hugo_goujian_geren_boke-2024.3.3.0.dist-info/top_level.txt
jingtai_wangzhan_goujian_shouce_shiyong_hugo_goujian_geren_boke-2024.3.3.0.dist-info/RECORD
